{
  "updated_at": "2026-04-23T23:01:20Z",
  "satellites_online": 3,
  "total_satellites": 12,
  "active_anomalies": 0,
  "anomalies": [],
  "active_ground_passes": 3,
  "records_today": 6216,
  "spire007": {},
  "all_satellites": {
    "SPIRE-009": {
      "satellite_id": "SPIRE-009",
      "obc_temperature_c": 32.8,
      "reaction_wheel_rpm": 3165.0,
      "power_draw_mw": 1800.0,
      "battery_voltage_v": 8.155,
      "solar_current_ma": 515.8,
      "rf_link_margin_db": 12.24,
      "attitude_status": "nominal",
      "last_seen": "2026-04-23 23:01:15.622693120"
    },
    "SPIRE-010": {
      "satellite_id": "SPIRE-010",
      "obc_temperature_c": 28.1,
      "reaction_wheel_rpm": 3255.0,
      "power_draw_mw": 1831.0,
      "battery_voltage_v": 8.137,
      "solar_current_ma": 535.1,
      "rf_link_margin_db": 12.95,
      "attitude_status": "nominal",
      "last_seen": "2026-04-23 22:59:27.628761088"
    },
    "SPIRE-011": {
      "satellite_id": "SPIRE-011",
      "obc_temperature_c": 29.1,
      "reaction_wheel_rpm": 3212.0,
      "power_draw_mw": 1812.0,
      "battery_voltage_v": 8.21,
      "solar_current_ma": 524.8,
      "rf_link_margin_db": 12.58,
      "attitude_status": "nominal",
      "last_seen": "2026-04-23 22:51:57.645143040"
    }
  }
}