{
  "updated_at": "2026-04-29T01:57:13Z",
  "satellites_online": 2,
  "total_satellites": 12,
  "active_anomalies": 0,
  "anomalies": [],
  "active_ground_passes": 3,
  "records_today": 5411,
  "spire007": {},
  "all_satellites": {
    "SPIRE-010": {
      "satellite_id": "SPIRE-010",
      "obc_temperature_c": 27.8,
      "reaction_wheel_rpm": 3250.0,
      "power_draw_mw": 1829.0,
      "battery_voltage_v": 8.266,
      "solar_current_ma": 520.2,
      "rf_link_margin_db": 12.09,
      "attitude_status": "nominal",
      "last_seen": "2026-04-29 01:57:08.494021888"
    },
    "SPIRE-011": {
      "satellite_id": "SPIRE-011",
      "obc_temperature_c": 29.4,
      "reaction_wheel_rpm": 3141.0,
      "power_draw_mw": 1805.0,
      "battery_voltage_v": 8.142,
      "solar_current_ma": 533.2,
      "rf_link_margin_db": 12.97,
      "attitude_status": "nominal",
      "last_seen": "2026-04-29 01:51:56.448816896"
    }
  }
}